linksmith/__init__.py
linksmith/cli.py
linksmith/model.py
linksmith/settings.py
linksmith/sphinx/__init__.py
linksmith/sphinx/cli.py
linksmith/sphinx/core.py
linksmith/sphinx/inventory.py
linksmith/sphinx/util.py
linksmith/sphinx/community/__init__.py
linksmith/sphinx/community/anansi.py
linksmith/sphinx/community/curated.yaml
linksmith/util/__init__.py
linksmith/util/data.py
linksmith/util/python.py
linksmith-0.0.2.dist-info/licenses/LICENSE
linksmith-0.0.2.dist-info/METADATA
linksmith-0.0.2.dist-info/WHEEL
linksmith-0.0.2.dist-info/entry_points.txt
linksmith-0.0.2.dist-info/top_level.txt
linksmith-0.0.2.dist-info/RECORD
