Metadata-Version: 2.4
Name: linksmith
Version: 0.0.2
Summary: A program for processing Hyperlinks, Sphinx references, and inventories.
Author-email: Andreas Motl <andreas.motl@panodata.org>
License: MIT License Copyright (c) 2024 Andreas Motl
Project-URL: changelog, https://github.com/tech-writing/linksmith/blob/main/CHANGES.md
Project-URL: documentation, https://linksmith.readthedocs.io/
Project-URL: homepage, https://linksmith.readthedocs.io/
Project-URL: repository, https://github.com/tech-writing/linksmith
Keywords: authoring,css,design,documentation,html,http,hyperlink,link,markdown,myst,referencing,restructuredtext,sphinx,swiss army knife,tech writing,toolbox,web
Classifier: Development Status :: 4 - Beta
Classifier: Environment :: Web Environment
Classifier: Framework :: Sphinx
Classifier: Intended Audience :: Customer Service
Classifier: Intended Audience :: Developers
Classifier: Intended Audience :: Education
Classifier: Intended Audience :: End Users/Desktop
Classifier: Intended Audience :: Information Technology
Classifier: Intended Audience :: Manufacturing
Classifier: Intended Audience :: Science/Research
Classifier: Intended Audience :: System Administrators
Classifier: Intended Audience :: Telecommunications Industry
Classifier: License :: OSI Approved :: MIT License
Classifier: Programming Language :: Python :: 3 :: Only
Classifier: Programming Language :: Python :: 3.9
Classifier: Programming Language :: Python :: 3.10
Classifier: Programming Language :: Python :: 3.11
Classifier: Programming Language :: Python :: 3.12
Classifier: Programming Language :: Python :: 3.13
Classifier: Programming Language :: Python :: 3.14
Classifier: Programming Language :: Python :: Implementation :: CPython
Classifier: Topic :: Documentation
Classifier: Topic :: Documentation :: Sphinx
Classifier: Topic :: Education
Classifier: Topic :: File Formats
Classifier: Topic :: Scientific/Engineering
Classifier: Topic :: Software Development :: Bug Tracking
Classifier: Topic :: Software Development :: Code Generators
Classifier: Topic :: Software Development :: Documentation
Classifier: Topic :: Software Development :: Libraries :: Python Modules
Classifier: Topic :: Text Processing
Classifier: Topic :: Text Processing :: Markup
Classifier: Topic :: Text Processing :: Markup :: HTML
Classifier: Topic :: Text Processing :: Markup :: Markdown
Classifier: Topic :: Text Processing :: Markup :: reStructuredText
Requires-Python: >=3.9
License-File: LICENSE
Requires-Dist: dynamic-imports<2
Requires-Dist: marko<3
Requires-Dist: myst-parser[linkify]<5,>=0.18
Requires-Dist: pueblo[cli]==0.0.11
Requires-Dist: pyyaml<7
Requires-Dist: requests<3
Requires-Dist: rich-click<2
Requires-Dist: sphinx<8.2
Requires-Dist: sphobjinv<2.4
Requires-Dist: tabulate<0.10
Requires-Dist: verlib2==0.3.1
Provides-Extra: develop
Requires-Dist: black<26; extra == "develop"
Requires-Dist: mypy<1.20; extra == "develop"
Requires-Dist: poethepoet<1; extra == "develop"
Requires-Dist: pyproject-fmt<3; extra == "develop"
Requires-Dist: ruff<0.15; extra == "develop"
Requires-Dist: validate-pyproject<1; extra == "develop"
Provides-Extra: docs
Requires-Dist: furo>=2024; extra == "docs"
Requires-Dist: sphinx<8.2; extra == "docs"
Requires-Dist: sphinx-autobuild>=2024; extra == "docs"
Requires-Dist: sphinx-copybutton<0.6; extra == "docs"
Requires-Dist: sphinx-design-elements<0.5; extra == "docs"
Provides-Extra: release
Requires-Dist: build<2; extra == "release"
Requires-Dist: keyring; extra == "release"
Requires-Dist: twine<7; extra == "release"
Provides-Extra: test
Requires-Dist: pytest<9; extra == "test"
Requires-Dist: pytest-cov<7; extra == "test"
Requires-Dist: sphinx-pytest<0.3; extra == "test"
Dynamic: license-file
